boltz_lab/__init__.py
boltz_lab/__main__.py
boltz_lab/cli.py
boltz_lab/client.py
boltz_lab/config.py
boltz_lab/exceptions.py
boltz_lab/models.py
boltz_lab/prediction_flags.py
boltz_lab/py.typed
boltz_lab/utils.py
boltz_lab-0.1.0.dist-info/licenses/LICENSE
boltz_lab-0.1.0.dist-info/METADATA
boltz_lab-0.1.0.dist-info/WHEEL
boltz_lab-0.1.0.dist-info/entry_points.txt
boltz_lab-0.1.0.dist-info/top_level.txt
boltz_lab-0.1.0.dist-info/RECORD
