Metadata-Version: 2.4
Name: boltz-lab
Version: 0.1.0
Summary: Python client for the Boltz Lab API
Author-email: Boltz PBC <support@boltz.bio>
License-Expression: MIT
Project-URL: Homepage, https://github.com/boltz-bio/boltz-lab-python
Project-URL: Repository, https://github.com/boltz-bio/boltz-lab-python
Keywords: boltz,api,client,molecular,prediction
Classifier: Development Status :: 3 - Alpha
Classifier: Intended Audience :: Developers
Classifier: Programming Language :: Python :: 3
Classifier: Programming Language :: Python :: 3.10
Classifier: Programming Language :: Python :: 3.11
Classifier: Programming Language :: Python :: 3.12
Requires-Python: >=3.10
License-File: LICENSE
Requires-Dist: httpx>=0.25.0
Requires-Dist: pydantic>=2.0
Requires-Dist: pyyaml>=6.0
Requires-Dist: click>=8.1
Requires-Dist: tenacity>=8.2.3
Requires-Dist: python-dotenv>=1.0.0
Requires-Dist: rich>=13.7.0
Dynamic: license-file
